mapsy/__init__.py
mapsy/color.py
mapsy/common.py
mapsy/geo_util.py
mapsy/icon/__init__.py
mapsy/icon/data/pin-24.png
mapsy/icon/data/pin-48.png
mapsy/icon/icon.py
mapsy/layer/__init__.py
mapsy/layer/attribution.py
mapsy/layer/background_layer.py
mapsy/layer/circle_layer.py
mapsy/layer/fill_layer.py
mapsy/layer/layer.py
mapsy/layer/line_layer.py
mapsy/layer/raster_layer.py
mapsy/layer/symbol_layer.py
mapsy/mapsy_map.py
mapsy/render/__init__.py
mapsy/render/cairo_backend.py
mapsy/render/context.py
mapsy/render/renderer.py
mapsy-0.3.1.dist-info/LICENSE
mapsy-0.3.1.dist-info/METADATA
mapsy-0.3.1.dist-info/WHEEL
mapsy-0.3.1.dist-info/RECORD
