Metadata-Version: 2.1
Name: mapsy
Version: 0.3.1
Summary: Mapsy is a Python library designed easily render static maps in python.
Home-page: https://github.com/ocell/mapsy
License: MIT
Author: Felix Horvat
Author-email: felix.horvat@ocell.io
Requires-Python: >=3.10,<4.0
Classifier: License :: OSI Approved :: MIT License
Classifier: Programming Language :: Python :: 3
Classifier: Programming Language :: Python :: 3.10
Classifier: Programming Language :: Python :: 3.11
Classifier: Programming Language :: Python :: 3.12
Requires-Dist: affine (>=2.4.0,<3.0.0)
Requires-Dist: mercantile (>=1.2.1,<2.0.0)
Requires-Dist: pillow (>=10.4.0,<11.0.0)
Requires-Dist: pycairo (>=1.26.1,<2.0.0)
Requires-Dist: pyproj (>=3.6.1,<4.0.0)
Requires-Dist: requests (>=2.32.3,<3.0.0)
Requires-Dist: shapely (>=2.0.4,<3.0.0)
Requires-Dist: urllib3 (>=2.6.1,<3.0.0)
Project-URL: Repository, https://github.com/ocell/mapsy
